seconometrics/__init__.py
seconometrics/correlation.py
tests/__init__.py
tests/test_correlation.py
seconometrics-0.8.dist-info/LICENSE
seconometrics-0.8.dist-info/METADATA
seconometrics-0.8.dist-info/WHEEL
seconometrics-0.8.dist-info/top_level.txt
seconometrics-0.8.dist-info/RECORD
